klogg/__init__.py
klogg/cli.py
klogg-0.1.7.dist-info/licenses/LICENSE
klogg-0.1.7.dist-info/METADATA
klogg-0.1.7.dist-info/WHEEL
klogg-0.1.7.dist-info/entry_points.txt
klogg-0.1.7.dist-info/top_level.txt
klogg-0.1.7.dist-info/RECORD
