Metadata-Version: 2.4
Name: klogg
Version: 0.1.7
Summary: Simple command line work logger
Author-email: Predrag Mandic <predrag@nul.one>
License: MIT
Project-URL: Homepage, https://gitlab.com/nul.one/klogg
Requires-Python: >=3.8
License-File: LICENSE
Requires-Dist: click>=8.0
Requires-Dist: click-aliases>=1.0
Dynamic: license-file
